bytewax_lever/__init__.py
bytewax_lever/html_to_text.py
bytewax_lever/lever_client.py
bytewax_lever/py.typed
bytewax_lever/types.py
bytewax_lever/inputs/__init__.py
bytewax_lever/inputs/posting_source.py
bytewax_lever-0.2.2.dist-info/METADATA
bytewax_lever-0.2.2.dist-info/WHEEL
bytewax_lever-0.2.2.dist-info/licenses/LICENSE
bytewax_lever-0.2.2.dist-info/RECORD
