Metadata-Version: 2.3
Name: bytewax-lever
Version: 0.2.2
Summary: Lever connectors for Bytewax
Project-URL: Repository, https://github.com/imnotjames/bytewax-lever.git
Project-URL: Issues, https://github.com/imnotjames/bytewax-lever/issues
Author-email: James Ward <james@notjam.es>
License: MIT License
Keywords: bytewax,lever
Requires-Python: >=3.12
Requires-Dist: bytewax>=0.21.0
Requires-Dist: requests>=2.32.3
